<?xml version="1.0" encoding="UTF-8"?>
<response>
      <control>
            <status>success</status>
            <senderid>MAKERMEDIA</senderid>
            <controlid>1443515401</controlid>
            <uniqueid>true</uniqueid>
            <dtdversion>2.1</dtdversion>
      </control>
      <operation>
            <authentication>
                  <status>success</status>
                  <userid>nli</userid>
                  <companyid>MAKERMEDIA</companyid>
                  <sessiontimestamp>2015-09-29T01:30:02-07:00</sessiontimestamp>
            </authentication>
            <result>
                  <status>success</status>
                  <function>get_accountbalances</function>
                  <controlid>1443515401-1</controlid>
                  <data>
                        <accountbalance>
                              <glaccountno>2001</glaccountno>
                              <startbalance>-1641044.68</startbalance>
                              <debits>1695191.19</debits>
                              <credits>1541736.12</credits>
                              <adjdebits>0.00</adjdebits>
                              <adjcredits>0.00</adjcredits>
                              <endbalance>-1487589.61</endbalance>
                        </accountbalance>
                        <accountbalance>
                              <glaccountno>2025</glaccountno>
                              <startbalance>50007.15</startbalance>
                              <debits>158528.69</debits>
                              <credits>517536.88</credits>
                              <adjdebits>0.00</adjdebits>
                              <adjcredits>0.00</adjcredits>
                              <endbalance>-309001.04</endbalance>
                        </accountbalance>
                  </data>
            </result>
            <result>
                  <status>success</status>
                  <function>get_accountbalances</function>
                  <controlid>1443515401-2</controlid>
                  <data>
                        <accountbalance>
                              <glaccountno>1100</glaccountno>
                              <startbalance>-54031.77</startbalance>
                              <debits>12227.06</debits>
                              <credits>0.00</credits>
                              <adjdebits>0.00</adjdebits>
                              <adjcredits>0.00</adjcredits>
                              <endbalance>-41804.71</endbalance>
                        </accountbalance>
                        <accountbalance>
                              <glaccountno>1101</glaccountno>
                              <startbalance>4000707.34</startbalance>
                              <debits>1721280.93</debits>
                              <credits>1210942.27</credits>
                              <adjdebits>0.00</adjdebits>
                              <adjcredits>0.00</adjcredits>
                              <endbalance>4511046</endbalance>
                        </accountbalance>
                        <accountbalance>
                              <glaccountno>1104</glaccountno>
                              <startbalance>-9057.63</startbalance>
                              <debits>0.00</debits>
                              <credits>0.00</credits>
                              <adjdebits>0.00</adjdebits>
                              <adjcredits>0.00</adjcredits>
                              <endbalance>-9057.63</endbalance>
                        </accountbalance>
                        <accountbalance>
                              <glaccountno>1201</glaccountno>
                              <startbalance>449957</startbalance>
                              <debits>0.00</debits>
                              <credits>422737</credits>
                              <adjdebits>0.00</adjdebits>
                              <adjcredits>0.00</adjcredits>
                              <endbalance>27220</endbalance>
                        </accountbalance>
                        <accountbalance>
                              <glaccountno>1202</glaccountno>
                              <startbalance>-411586.04</startbalance>
                              <debits>0.00</debits>
                              <credits>184873.2</credits>
                              <adjdebits>0.00</adjdebits>
                              <adjcredits>0.00</adjcredits>
                              <endbalance>-596459.24</endbalance>
                        </accountbalance>
                        <accountbalance>
                              <glaccountno>1205</glaccountno>
                              <startbalance>-548472.06</startbalance>
                              <debits>0.00</debits>
                              <credits>0.00</credits>
                              <adjdebits>0.00</adjdebits>
                              <adjcredits>0.00</adjcredits>
                              <endbalance>-548472.06</endbalance>
                        </accountbalance>
                        <accountbalance>
                              <glaccountno>1221</glaccountno>
                              <startbalance>20999.99</startbalance>
                              <debits>0.00</debits>
                              <credits>0.00</credits>
                              <adjdebits>0.00</adjdebits>
                              <adjcredits>0.00</adjcredits>
                              <endbalance>20999.99</endbalance>
                        </accountbalance>
                        <accountbalance>
                              <glaccountno>1241</glaccountno>
                              <startbalance>-291.73</startbalance>
                              <debits>0.00</debits>
                              <credits>334.62</credits>
                              <adjdebits>0.00</adjdebits>
                              <adjcredits>0.00</adjcredits>
                              <endbalance>-626.35</endbalance>
                        </accountbalance>
                        <accountbalance>
                              <glaccountno>1242</glaccountno>
                              <startbalance>9580.77</startbalance>
                              <debits>0.00</debits>
                              <credits>0.00</credits>
                              <adjdebits>0.00</adjdebits>
                              <adjcredits>0.00</adjcredits>
                              <endbalance>9580.77</endbalance>
                        </accountbalance>
                  </data>
            </result>
            <result>
                  <status>success</status>
                  <function>get_accountbalances</function>
                  <controlid>1443515401-2</controlid>
                  <data>
                        <accountbalance>
                              <glaccountno>4105</glaccountno>
                              <startbalance>0</startbalance>
                              <debits>0.00</debits>
                              <credits>284420.3</credits>
                              <adjdebits>0.00</adjdebits>
                              <adjcredits>0.00</adjcredits>
                              <endbalance>-284420.3</endbalance>
                        </accountbalance>
                        <accountbalance>
                              <glaccountno>4107</glaccountno>
                              <startbalance>0</startbalance>
                              <debits>184873.2</debits>
                              <credits>0.00</credits>
                              <adjdebits>0.00</adjdebits>
                              <adjcredits>0.00</adjcredits>
                              <endbalance>184873.2</endbalance>
                        </accountbalance>
                        <accountbalance>
                              <glaccountno>4108</glaccountno>
                              <startbalance>0</startbalance>
                              <debits>24.75</debits>
                              <credits>4458.29</credits>
                              <adjdebits>0.00</adjdebits>
                              <adjcredits>0.00</adjcredits>
                              <endbalance>-4433.54</endbalance>
                        </accountbalance>
                        <accountbalance>
                              <glaccountno>4113</glaccountno>
                              <startbalance>0</startbalance>
                              <debits>69911.95</debits>
                              <credits>143446.61</credits>
                              <adjdebits>0.00</adjdebits>
                              <adjcredits>0.00</adjcredits>
                              <endbalance>-73534.66</endbalance>
                        </accountbalance>
                        <accountbalance>
                              <glaccountno>4201</glaccountno>
                              <startbalance>0</startbalance>
                              <debits>291799.43</debits>
                              <credits>286218.01</credits>
                              <adjdebits>0.00</adjdebits>
                              <adjcredits>0.00</adjcredits>
                              <endbalance>5581.42</endbalance>
                        </accountbalance>
                        <accountbalance>
                              <glaccountno>4203</glaccountno>
                              <startbalance>0</startbalance>
                              <debits>0.00</debits>
                              <credits>5000</credits>
                              <adjdebits>0.00</adjdebits>
                              <adjcredits>0.00</adjcredits>
                              <endbalance>-5000</endbalance>
                        </accountbalance>
                        <accountbalance>
                              <glaccountno>4205</glaccountno>
                              <startbalance>0</startbalance>
                              <debits>82250</debits>
                              <credits>53671.95</credits>
                              <adjdebits>0.00</adjdebits>
                              <adjcredits>0.00</adjcredits>
                              <endbalance>28578.05</endbalance>
                        </accountbalance>
                        <accountbalance>
                              <glaccountno>4207</glaccountno>
                              <startbalance>0</startbalance>
                              <debits>0.00</debits>
                              <credits>13</credits>
                              <adjdebits>0.00</adjdebits>
                              <adjcredits>0.00</adjcredits>
                              <endbalance>-13</endbalance>
                        </accountbalance>
                        <accountbalance>
                              <glaccountno>4209</glaccountno>
                              <startbalance>0</startbalance>
                              <debits>4500</debits>
                              <credits>16690.82</credits>
                              <adjdebits>0.00</adjdebits>
                              <adjcredits>0.00</adjcredits>
                              <endbalance>-12190.82</endbalance>
                        </accountbalance>
                        <accountbalance>
                              <glaccountno>4212</glaccountno>
                              <startbalance>0</startbalance>
                              <debits>0.00</debits>
                              <credits>7605.36</credits>
                              <adjdebits>0.00</adjdebits>
                              <adjcredits>0.00</adjcredits>
                              <endbalance>-7605.36</endbalance>
                        </accountbalance>
                        <accountbalance>
                              <glaccountno>4213</glaccountno>
                              <startbalance>0</startbalance>
                              <debits>0.00</debits>
                              <credits>1189.89</credits>
                              <adjdebits>0.00</adjdebits>
                              <adjcredits>0.00</adjcredits>
                              <endbalance>-1189.89</endbalance>
                        </accountbalance>
                        <accountbalance>
                              <glaccountno>4301</glaccountno>
                              <startbalance>0</startbalance>
                              <debits>0.00</debits>
                              <credits>32353</credits>
                              <adjdebits>0.00</adjdebits>
                              <adjcredits>0.00</adjcredits>
                              <endbalance>-32353</endbalance>
                        </accountbalance>
                        <accountbalance>
                              <glaccountno>4307</glaccountno>
                              <startbalance>0</startbalance>
                              <debits>0.00</debits>
                              <credits>12500</credits>
                              <adjdebits>0.00</adjdebits>
                              <adjcredits>0.00</adjcredits>
                              <endbalance>-12500</endbalance>
                        </accountbalance>
                        <accountbalance>
                              <glaccountno>4309</glaccountno>
                              <startbalance>0</startbalance>
                              <debits>0.00</debits>
                              <credits>5438</credits>
                              <adjdebits>0.00</adjdebits>
                              <adjcredits>0.00</adjcredits>
                              <endbalance>-5438</endbalance>
                        </accountbalance>
                        <accountbalance>
                              <glaccountno>4401</glaccountno>
                              <startbalance>0</startbalance>
                              <debits>228060.63</debits>
                              <credits>570455.3</credits>
                              <adjdebits>0.00</adjdebits>
                              <adjcredits>0.00</adjcredits>
                              <endbalance>-342394.67</endbalance>
                        </accountbalance>
                        <accountbalance>
                              <glaccountno>4403</glaccountno>
                              <startbalance>0</startbalance>
                              <debits>2718.3</debits>
                              <credits>0.00</credits>
                              <adjdebits>0.00</adjdebits>
                              <adjcredits>0.00</adjcredits>
                              <endbalance>2718.3</endbalance>
                        </accountbalance>
                        <accountbalance>
                              <glaccountno>4417</glaccountno>
                              <startbalance>0</startbalance>
                              <debits>210.46</debits>
                              <credits>0.00</credits>
                              <adjdebits>0.00</adjdebits>
                              <adjcredits>0.00</adjcredits>
                              <endbalance>210.46</endbalance>
                        </accountbalance>
                        <accountbalance>
                              <glaccountno>4421</glaccountno>
                              <startbalance>0</startbalance>
                              <debits>0.00</debits>
                              <credits>139.34</credits>
                              <adjdebits>0.00</adjdebits>
                              <adjcredits>0.00</adjcredits>
                              <endbalance>-139.34</endbalance>
                        </accountbalance>
                        <accountbalance>
                              <glaccountno>4423</glaccountno>
                              <startbalance>0</startbalance>
                              <debits>50000</debits>
                              <credits>0.00</credits>
                              <adjdebits>0.00</adjdebits>
                              <adjcredits>0.00</adjcredits>
                              <endbalance>50000</endbalance>
                        </accountbalance>
                        <accountbalance>
                              <glaccountno>4511</glaccountno>
                              <startbalance>0</startbalance>
                              <debits>0.00</debits>
                              <credits>242715.05</credits>
                              <adjdebits>0.00</adjdebits>
                              <adjcredits>0.00</adjcredits>
                              <endbalance>-242715.05</endbalance>
                        </accountbalance>
                        <accountbalance>
                              <glaccountno>4551</glaccountno>
                              <startbalance>0</startbalance>
                              <debits>26995</debits>
                              <credits>400020</credits>
                              <adjdebits>0.00</adjdebits>
                              <adjcredits>0.00</adjcredits>
                              <endbalance>-373025</endbalance>
                        </accountbalance>
                        <accountbalance>
                              <glaccountno>4554</glaccountno>
                              <startbalance>0</startbalance>
                              <debits>0.00</debits>
                              <credits>28440</credits>
                              <adjdebits>0.00</adjdebits>
                              <adjcredits>0.00</adjcredits>
                              <endbalance>-28440</endbalance>
                        </accountbalance>
                        <accountbalance>
                              <glaccountno>4555</glaccountno>
                              <startbalance>0</startbalance>
                              <debits>0.00</debits>
                              <credits>37511.9</credits>
                              <adjdebits>0.00</adjdebits>
                              <adjcredits>0.00</adjcredits>
                              <endbalance>-37511.9</endbalance>
                        </accountbalance>
                        <accountbalance>
                              <glaccountno>4580</glaccountno>
                              <startbalance>0</startbalance>
                              <debits>0.00</debits>
                              <credits>779</credits>
                              <adjdebits>0.00</adjdebits>
                              <adjcredits>0.00</adjcredits>
                              <endbalance>-779</endbalance>
                        </accountbalance>
                        <accountbalance>
                              <glaccountno>4581</glaccountno>
                              <startbalance>0</startbalance>
                              <debits>1203.12</debits>
                              <credits>0.00</credits>
                              <adjdebits>0.00</adjdebits>
                              <adjcredits>0.00</adjcredits>
                              <endbalance>1203.12</endbalance>
                        </accountbalance>
                        <accountbalance>
                              <glaccountno>4583</glaccountno>
                              <startbalance>0</startbalance>
                              <debits>0.00</debits>
                              <credits>9710</credits>
                              <adjdebits>0.00</adjdebits>
                              <adjcredits>0.00</adjcredits>
                              <endbalance>-9710</endbalance>
                        </accountbalance>
                        <accountbalance>
                              <glaccountno>4584</glaccountno>
                              <startbalance>0</startbalance>
                              <debits>0.00</debits>
                              <credits>12000</credits>
                              <adjdebits>0.00</adjdebits>
                              <adjcredits>0.00</adjcredits>
                              <endbalance>-12000</endbalance>
                        </accountbalance>
                        <accountbalance>
                              <glaccountno>4599</glaccountno>
                              <startbalance>0</startbalance>
                              <debits>0.00</debits>
                              <credits>1931850.38</credits>
                              <adjdebits>0.00</adjdebits>
                              <adjcredits>0.00</adjcredits>
                              <endbalance>-1931850.38</endbalance>
                        </accountbalance>
                        <accountbalance>
                              <glaccountno>5101</glaccountno>
                              <startbalance>0</startbalance>
                              <debits>87936.01</debits>
                              <credits>0.00</credits>
                              <adjdebits>0.00</adjdebits>
                              <adjcredits>0.00</adjcredits>
                              <endbalance>87936.01</endbalance>
                        </accountbalance>
                        <accountbalance>
                              <glaccountno>5103</glaccountno>
                              <startbalance>0</startbalance>
                              <debits>6397.57</debits>
                              <credits>0.00</credits>
                              <adjdebits>0.00</adjdebits>
                              <adjcredits>0.00</adjcredits>
                              <endbalance>6397.57</endbalance>
                        </accountbalance>
                        <accountbalance>
                              <glaccountno>5105</glaccountno>
                              <startbalance>0</startbalance>
                              <debits>11250</debits>
                              <credits>0.00</credits>
                              <adjdebits>0.00</adjdebits>
                              <adjcredits>0.00</adjcredits>
                              <endbalance>11250</endbalance>
                        </accountbalance>
                        <accountbalance>
                              <glaccountno>5107</glaccountno>
                              <startbalance>0</startbalance>
                              <debits>7742.45</debits>
                              <credits>0.00</credits>
                              <adjdebits>0.00</adjdebits>
                              <adjcredits>0.00</adjcredits>
                              <endbalance>7742.45</endbalance>
                        </accountbalance>
                        <accountbalance>
                              <glaccountno>5109</glaccountno>
                              <startbalance>0</startbalance>
                              <debits>12429.6</debits>
                              <credits>0.00</credits>
                              <adjdebits>0.00</adjdebits>
                              <adjcredits>0.00</adjcredits>
                              <endbalance>12429.6</endbalance>
                        </accountbalance>
                        <accountbalance>
                              <glaccountno>5111</glaccountno>
                              <startbalance>0</startbalance>
                              <debits>18799.23</debits>
                              <credits>0.00</credits>
                              <adjdebits>0.00</adjdebits>
                              <adjcredits>0.00</adjcredits>
                              <endbalance>18799.23</endbalance>
                        </accountbalance>
                        <accountbalance>
                              <glaccountno>5117</glaccountno>
                              <startbalance>0</startbalance>
                              <debits>1075.88</debits>
                              <credits>0.00</credits>
                              <adjdebits>0.00</adjdebits>
                              <adjcredits>0.00</adjcredits>
                              <endbalance>1075.88</endbalance>
                        </accountbalance>
                        <accountbalance>
                              <glaccountno>5123</glaccountno>
                              <startbalance>0</startbalance>
                              <debits>573.66</debits>
                              <credits>0.00</credits>
                              <adjdebits>0.00</adjdebits>
                              <adjcredits>0.00</adjcredits>
                              <endbalance>573.66</endbalance>
                        </accountbalance>
                        <accountbalance>
                              <glaccountno>5199</glaccountno>
                              <startbalance>0</startbalance>
                              <debits>150</debits>
                              <credits>0.00</credits>
                              <adjdebits>0.00</adjdebits>
                              <adjcredits>0.00</adjcredits>
                              <endbalance>150</endbalance>
                        </accountbalance>
                        <accountbalance>
                              <glaccountno>5201</glaccountno>
                              <startbalance>0</startbalance>
                              <debits>11806.5</debits>
                              <credits>30539.75</credits>
                              <adjdebits>0.00</adjdebits>
                              <adjcredits>0.00</adjcredits>
                              <endbalance>-18733.25</endbalance>
                        </accountbalance>
                        <accountbalance>
                              <glaccountno>5202</glaccountno>
                              <startbalance>0</startbalance>
                              <debits>463.33</debits>
                              <credits>0.00</credits>
                              <adjdebits>0.00</adjdebits>
                              <adjcredits>0.00</adjcredits>
                              <endbalance>463.33</endbalance>
                        </accountbalance>
                        <accountbalance>
                              <glaccountno>5205</glaccountno>
                              <startbalance>0</startbalance>
                              <debits>22444.36</debits>
                              <credits>10000</credits>
                              <adjdebits>0.00</adjdebits>
                              <adjcredits>0.00</adjcredits>
                              <endbalance>12444.36</endbalance>
                        </accountbalance>
                        <accountbalance>
                              <glaccountno>5209</glaccountno>
                              <startbalance>0</startbalance>
                              <debits>73209.33</debits>
                              <credits>41400</credits>
                              <adjdebits>0.00</adjdebits>
                              <adjcredits>0.00</adjcredits>
                              <endbalance>31809.33</endbalance>
                        </accountbalance>
                        <accountbalance>
                              <glaccountno>5305</glaccountno>
                              <startbalance>0</startbalance>
                              <debits>3040</debits>
                              <credits>0.00</credits>
                              <adjdebits>0.00</adjdebits>
                              <adjcredits>0.00</adjcredits>
                              <endbalance>3040</endbalance>
                        </accountbalance>
                        <accountbalance>
                              <glaccountno>5307</glaccountno>
                              <startbalance>0</startbalance>
                              <debits>8030</debits>
                              <credits>0.00</credits>
                              <adjdebits>0.00</adjdebits>
                              <adjcredits>0.00</adjcredits>
                              <endbalance>8030</endbalance>
                        </accountbalance>
                        <accountbalance>
                              <glaccountno>5311</glaccountno>
                              <startbalance>0</startbalance>
                              <debits>10300</debits>
                              <credits>0.00</credits>
                              <adjdebits>0.00</adjdebits>
                              <adjcredits>0.00</adjcredits>
                              <endbalance>10300</endbalance>
                        </accountbalance>
                        <accountbalance>
                              <glaccountno>5401</glaccountno>
                              <startbalance>0</startbalance>
                              <debits>220772.97</debits>
                              <credits>0.00</credits>
                              <adjdebits>0.00</adjdebits>
                              <adjcredits>0.00</adjcredits>
                              <endbalance>220772.97</endbalance>
                        </accountbalance>
                        <accountbalance>
                              <glaccountno>5403</glaccountno>
                              <startbalance>0</startbalance>
                              <debits>2249.63</debits>
                              <credits>0.00</credits>
                              <adjdebits>0.00</adjdebits>
                              <adjcredits>0.00</adjcredits>
                              <endbalance>2249.63</endbalance>
                        </accountbalance>
                        <accountbalance>
                              <glaccountno>5405</glaccountno>
                              <startbalance>0</startbalance>
                              <debits>14337.36</debits>
                              <credits>18690.21</credits>
                              <adjdebits>0.00</adjdebits>
                              <adjcredits>0.00</adjcredits>
                              <endbalance>-4352.85</endbalance>
                        </accountbalance>
                        <accountbalance>
                              <glaccountno>5407</glaccountno>
                              <startbalance>0</startbalance>
                              <debits>19658.56</debits>
                              <credits>5598.9</credits>
                              <adjdebits>0.00</adjdebits>
                              <adjcredits>0.00</adjcredits>
                              <endbalance>14059.66</endbalance>
                        </accountbalance>
                        <accountbalance>
                              <glaccountno>5410</glaccountno>
                              <startbalance>0</startbalance>
                              <debits>500</debits>
                              <credits>0.00</credits>
                              <adjdebits>0.00</adjdebits>
                              <adjcredits>0.00</adjcredits>
                              <endbalance>500</endbalance>
                        </accountbalance>
                        <accountbalance>
                              <glaccountno>5423</glaccountno>
                              <startbalance>0</startbalance>
                              <debits>777.59</debits>
                              <credits>0.00</credits>
                              <adjdebits>0.00</adjdebits>
                              <adjcredits>0.00</adjcredits>
                              <endbalance>777.59</endbalance>
                        </accountbalance>
                        <accountbalance>
                              <glaccountno>5441</glaccountno>
                              <startbalance>0</startbalance>
                              <debits>511.43</debits>
                              <credits>0.00</credits>
                              <adjdebits>0.00</adjdebits>
                              <adjcredits>0.00</adjcredits>
                              <endbalance>511.43</endbalance>
                        </accountbalance>
                        <accountbalance>
                              <glaccountno>5451</glaccountno>
                              <startbalance>0</startbalance>
                              <debits>29.61</debits>
                              <credits>0.00</credits>
                              <adjdebits>0.00</adjdebits>
                              <adjcredits>0.00</adjcredits>
                              <endbalance>29.61</endbalance>
                        </accountbalance>
                        <accountbalance>
                              <glaccountno>5511</glaccountno>
                              <startbalance>0</startbalance>
                              <debits>7500</debits>
                              <credits>0.00</credits>
                              <adjdebits>0.00</adjdebits>
                              <adjcredits>0.00</adjcredits>
                              <endbalance>7500</endbalance>
                        </accountbalance>
                        <accountbalance>
                              <glaccountno>5513</glaccountno>
                              <startbalance>0</startbalance>
                              <debits>14579.85</debits>
                              <credits>0.00</credits>
                              <adjdebits>0.00</adjdebits>
                              <adjcredits>0.00</adjcredits>
                              <endbalance>14579.85</endbalance>
                        </accountbalance>
                        <accountbalance>
                              <glaccountno>5515</glaccountno>
                              <startbalance>0</startbalance>
                              <debits>3000</debits>
                              <credits>0.00</credits>
                              <adjdebits>0.00</adjdebits>
                              <adjcredits>0.00</adjcredits>
                              <endbalance>3000</endbalance>
                        </accountbalance>
                        <accountbalance>
                              <glaccountno>5522</glaccountno>
                              <startbalance>0</startbalance>
                              <debits>164527.38</debits>
                              <credits>0.00</credits>
                              <adjdebits>0.00</adjdebits>
                              <adjcredits>0.00</adjcredits>
                              <endbalance>164527.38</endbalance>
                        </accountbalance>
                        <accountbalance>
                              <glaccountno>5523</glaccountno>
                              <startbalance>0</startbalance>
                              <debits>62548.75</debits>
                              <credits>0.00</credits>
                              <adjdebits>0.00</adjdebits>
                              <adjcredits>0.00</adjcredits>
                              <endbalance>62548.75</endbalance>
                        </accountbalance>
                        <accountbalance>
                              <glaccountno>5531</glaccountno>
                              <startbalance>0</startbalance>
                              <debits>12915</debits>
                              <credits>0.00</credits>
                              <adjdebits>0.00</adjdebits>
                              <adjcredits>0.00</adjcredits>
                              <endbalance>12915</endbalance>
                        </accountbalance>
                        <accountbalance>
                              <glaccountno>5533</glaccountno>
                              <startbalance>0</startbalance>
                              <debits>18239.8</debits>
                              <credits>0.00</credits>
                              <adjdebits>0.00</adjdebits>
                              <adjcredits>0.00</adjcredits>
                              <endbalance>18239.8</endbalance>
                        </accountbalance>
                        <accountbalance>
                              <glaccountno>5553</glaccountno>
                              <startbalance>0</startbalance>
                              <debits>10000</debits>
                              <credits>0.00</credits>
                              <adjdebits>0.00</adjdebits>
                              <adjcredits>0.00</adjcredits>
                              <endbalance>10000</endbalance>
                        </accountbalance>
                        <accountbalance>
                              <glaccountno>5560</glaccountno>
                              <startbalance>0</startbalance>
                              <debits>9844.9</debits>
                              <credits>0.00</credits>
                              <adjdebits>0.00</adjdebits>
                              <adjcredits>0.00</adjcredits>
                              <endbalance>9844.9</endbalance>
                        </accountbalance>
                        <accountbalance>
                              <glaccountno>5570</glaccountno>
                              <startbalance>0</startbalance>
                              <debits>7178.23</debits>
                              <credits>0.00</credits>
                              <adjdebits>0.00</adjdebits>
                              <adjcredits>0.00</adjcredits>
                              <endbalance>7178.23</endbalance>
                        </accountbalance>
                        <accountbalance>
                              <glaccountno>5571</glaccountno>
                              <startbalance>0</startbalance>
                              <debits>30636.05</debits>
                              <credits>0.00</credits>
                              <adjdebits>0.00</adjdebits>
                              <adjcredits>0.00</adjcredits>
                              <endbalance>30636.05</endbalance>
                        </accountbalance>
                        <accountbalance>
                              <glaccountno>5572</glaccountno>
                              <startbalance>0</startbalance>
                              <debits>20768.52</debits>
                              <credits>0.00</credits>
                              <adjdebits>0.00</adjdebits>
                              <adjcredits>0.00</adjcredits>
                              <endbalance>20768.52</endbalance>
                        </accountbalance>
                        <accountbalance>
                              <glaccountno>5582</glaccountno>
                              <startbalance>0</startbalance>
                              <debits>4306.78</debits>
                              <credits>0.00</credits>
                              <adjdebits>0.00</adjdebits>
                              <adjcredits>0.00</adjcredits>
                              <endbalance>4306.78</endbalance>
                        </accountbalance>
                        <accountbalance>
                              <glaccountno>5583</glaccountno>
                              <startbalance>0</startbalance>
                              <debits>40</debits>
                              <credits>0.00</credits>
                              <adjdebits>0.00</adjdebits>
                              <adjcredits>0.00</adjcredits>
                              <endbalance>40</endbalance>
                        </accountbalance>
                        <accountbalance>
                              <glaccountno>5584</glaccountno>
                              <startbalance>0</startbalance>
                              <debits>175561.75</debits>
                              <credits>86663.15</credits>
                              <adjdebits>0.00</adjdebits>
                              <adjcredits>0.00</adjcredits>
                              <endbalance>88898.6</endbalance>
                        </accountbalance>
                        <accountbalance>
                              <glaccountno>5591</glaccountno>
                              <startbalance>0</startbalance>
                              <debits>72894.41</debits>
                              <credits>0.00</credits>
                              <adjdebits>0.00</adjdebits>
                              <adjcredits>0.00</adjcredits>
                              <endbalance>72894.41</endbalance>
                        </accountbalance>
                        <accountbalance>
                              <glaccountno>5592</glaccountno>
                              <startbalance>0</startbalance>
                              <debits>46968.17</debits>
                              <credits>0.00</credits>
                              <adjdebits>0.00</adjdebits>
                              <adjcredits>0.00</adjcredits>
                              <endbalance>46968.17</endbalance>
                        </accountbalance>
                        <accountbalance>
                              <glaccountno>5596</glaccountno>
                              <startbalance>0</startbalance>
                              <debits>500</debits>
                              <credits>0.00</credits>
                              <adjdebits>0.00</adjdebits>
                              <adjcredits>0.00</adjcredits>
                              <endbalance>500</endbalance>
                        </accountbalance>
                        <accountbalance>
                              <glaccountno>5601</glaccountno>
                              <startbalance>0</startbalance>
                              <debits>2150</debits>
                              <credits>0.00</credits>
                              <adjdebits>0.00</adjdebits>
                              <adjcredits>0.00</adjcredits>
                              <endbalance>2150</endbalance>
                        </accountbalance>
                        <accountbalance>
                              <glaccountno>5603</glaccountno>
                              <startbalance>0</startbalance>
                              <debits>7443.75</debits>
                              <credits>0.00</credits>
                              <adjdebits>0.00</adjdebits>
                              <adjcredits>0.00</adjcredits>
                              <endbalance>7443.75</endbalance>
                        </accountbalance>
                        <accountbalance>
                              <glaccountno>5651</glaccountno>
                              <startbalance>0</startbalance>
                              <debits>183784</debits>
                              <credits>0.00</credits>
                              <adjdebits>0.00</adjdebits>
                              <adjcredits>0.00</adjcredits>
                              <endbalance>183784</endbalance>
                        </accountbalance>
                        <accountbalance>
                              <glaccountno>5669</glaccountno>
                              <startbalance>0</startbalance>
                              <debits>577780.06</debits>
                              <credits>0.00</credits>
                              <adjdebits>0.00</adjdebits>
                              <adjcredits>0.00</adjcredits>
                              <endbalance>577780.06</endbalance>
                        </accountbalance>
                        <accountbalance>
                              <glaccountno>7114</glaccountno>
                              <startbalance>0</startbalance>
                              <debits>46.6</debits>
                              <credits>0.00</credits>
                              <adjdebits>0.00</adjdebits>
                              <adjcredits>0.00</adjcredits>
                              <endbalance>46.6</endbalance>
                        </accountbalance>
                        <accountbalance>
                              <glaccountno>7115</glaccountno>
                              <startbalance>0</startbalance>
                              <debits>0.00</debits>
                              <credits>7421.59</credits>
                              <adjdebits>0.00</adjdebits>
                              <adjcredits>0.00</adjcredits>
                              <endbalance>-7421.59</endbalance>
                        </accountbalance>
                        <accountbalance>
                              <glaccountno>7119</glaccountno>
                              <startbalance>0</startbalance>
                              <debits>0.00</debits>
                              <credits>11.4</credits>
                              <adjdebits>0.00</adjdebits>
                              <adjcredits>0.00</adjcredits>
                              <endbalance>-11.4</endbalance>
                        </accountbalance>
                        <accountbalance>
                              <glaccountno>7129</glaccountno>
                              <startbalance>0</startbalance>
                              <debits>5583.72</debits>
                              <credits>0.00</credits>
                              <adjdebits>0.00</adjdebits>
                              <adjcredits>0.00</adjcredits>
                              <endbalance>5583.72</endbalance>
                        </accountbalance>
                        <accountbalance>
                              <glaccountno>7133</glaccountno>
                              <startbalance>0</startbalance>
                              <debits>0.00</debits>
                              <credits>1.3</credits>
                              <adjdebits>0.00</adjdebits>
                              <adjcredits>0.00</adjcredits>
                              <endbalance>-1.3</endbalance>
                        </accountbalance>
                        <accountbalance>
                              <glaccountno>7201</glaccountno>
                              <startbalance>0</startbalance>
                              <debits>68822.54</debits>
                              <credits>29012.83</credits>
                              <adjdebits>0.00</adjdebits>
                              <adjcredits>0.00</adjcredits>
                              <endbalance>39809.71</endbalance>
                        </accountbalance>
                        <accountbalance>
                              <glaccountno>7207</glaccountno>
                              <startbalance>0</startbalance>
                              <debits>470.12</debits>
                              <credits>0.00</credits>
                              <adjdebits>0.00</adjdebits>
                              <adjcredits>0.00</adjcredits>
                              <endbalance>470.12</endbalance>
                        </accountbalance>
                        <accountbalance>
                              <glaccountno>7307</glaccountno>
                              <startbalance>0</startbalance>
                              <debits>2057.61</debits>
                              <credits>0.00</credits>
                              <adjdebits>0.00</adjdebits>
                              <adjcredits>0.00</adjcredits>
                              <endbalance>2057.61</endbalance>
                        </accountbalance>
                        <accountbalance>
                              <glaccountno>7315</glaccountno>
                              <startbalance>0</startbalance>
                              <debits>12308.5</debits>
                              <credits>0.00</credits>
                              <adjdebits>0.00</adjdebits>
                              <adjcredits>0.00</adjcredits>
                              <endbalance>12308.5</endbalance>
                        </accountbalance>
                        <accountbalance>
                              <glaccountno>7319</glaccountno>
                              <startbalance>0</startbalance>
                              <debits>4065.6</debits>
                              <credits>0.00</credits>
                              <adjdebits>0.00</adjdebits>
                              <adjcredits>0.00</adjcredits>
                              <endbalance>4065.6</endbalance>
                        </accountbalance>
                        <accountbalance>
                              <glaccountno>7323</glaccountno>
                              <startbalance>0</startbalance>
                              <debits>4243.16</debits>
                              <credits>0.00</credits>
                              <adjdebits>0.00</adjdebits>
                              <adjcredits>0.00</adjcredits>
                              <endbalance>4243.16</endbalance>
                        </accountbalance>
                        <accountbalance>
                              <glaccountno>7325</glaccountno>
                              <startbalance>0</startbalance>
                              <debits>247.82</debits>
                              <credits>0.00</credits>
                              <adjdebits>0.00</adjdebits>
                              <adjcredits>0.00</adjcredits>
                              <endbalance>247.82</endbalance>
                        </accountbalance>
                        <accountbalance>
                              <glaccountno>7331</glaccountno>
                              <startbalance>0</startbalance>
                              <debits>39</debits>
                              <credits>0.00</credits>
                              <adjdebits>0.00</adjdebits>
                              <adjcredits>0.00</adjcredits>
                              <endbalance>39</endbalance>
                        </accountbalance>
                        <accountbalance>
                              <glaccountno>7501</glaccountno>
                              <startbalance>0</startbalance>
                              <debits>1515.8</debits>
                              <credits>0.00</credits>
                              <adjdebits>0.00</adjdebits>
                              <adjcredits>0.00</adjcredits>
                              <endbalance>1515.8</endbalance>
                        </accountbalance>
                        <accountbalance>
                              <glaccountno>7505</glaccountno>
                              <startbalance>0</startbalance>
                              <debits>96.84</debits>
                              <credits>0.00</credits>
                              <adjdebits>0.00</adjdebits>
                              <adjcredits>0.00</adjcredits>
                              <endbalance>96.84</endbalance>
                        </accountbalance>
                        <accountbalance>
                              <glaccountno>7509</glaccountno>
                              <startbalance>0</startbalance>
                              <debits>30.98</debits>
                              <credits>0.00</credits>
                              <adjdebits>0.00</adjdebits>
                              <adjcredits>0.00</adjcredits>
                              <endbalance>30.98</endbalance>
                        </accountbalance>
                        <accountbalance>
                              <glaccountno>7511</glaccountno>
                              <startbalance>0</startbalance>
                              <debits>92.4</debits>
                              <credits>0.00</credits>
                              <adjdebits>0.00</adjdebits>
                              <adjcredits>0.00</adjcredits>
                              <endbalance>92.4</endbalance>
                        </accountbalance>
                        <accountbalance>
                              <glaccountno>7513</glaccountno>
                              <startbalance>0</startbalance>
                              <debits>1701.98</debits>
                              <credits>0.00</credits>
                              <adjdebits>0.00</adjdebits>
                              <adjcredits>0.00</adjcredits>
                              <endbalance>1701.98</endbalance>
                        </accountbalance>
                        <accountbalance>
                              <glaccountno>7605</glaccountno>
                              <startbalance>0</startbalance>
                              <debits>10963</debits>
                              <credits>0.00</credits>
                              <adjdebits>0.00</adjdebits>
                              <adjcredits>0.00</adjcredits>
                              <endbalance>10963</endbalance>
                        </accountbalance>
                        <accountbalance>
                              <glaccountno>7609</glaccountno>
                              <startbalance>0</startbalance>
                              <debits>325</debits>
                              <credits>0.00</credits>
                              <adjdebits>0.00</adjdebits>
                              <adjcredits>0.00</adjcredits>
                              <endbalance>325</endbalance>
                        </accountbalance>
                        <accountbalance>
                              <glaccountno>7611</glaccountno>
                              <startbalance>0</startbalance>
                              <debits>5825</debits>
                              <credits>0.00</credits>
                              <adjdebits>0.00</adjdebits>
                              <adjcredits>0.00</adjcredits>
                              <endbalance>5825</endbalance>
                        </accountbalance>
                        <accountbalance>
                              <glaccountno>7705</glaccountno>
                              <startbalance>0</startbalance>
                              <debits>5179.42</debits>
                              <credits>0.00</credits>
                              <adjdebits>0.00</adjdebits>
                              <adjcredits>0.00</adjcredits>
                              <endbalance>5179.42</endbalance>
                        </accountbalance>
                        <accountbalance>
                              <glaccountno>7710</glaccountno>
                              <startbalance>0</startbalance>
                              <debits>500</debits>
                              <credits>0.00</credits>
                              <adjdebits>0.00</adjdebits>
                              <adjcredits>0.00</adjcredits>
                              <endbalance>500</endbalance>
                        </accountbalance>
                        <accountbalance>
                              <glaccountno>7713</glaccountno>
                              <startbalance>0</startbalance>
                              <debits>22102.5</debits>
                              <credits>0.00</credits>
                              <adjdebits>0.00</adjdebits>
                              <adjcredits>0.00</adjcredits>
                              <endbalance>22102.5</endbalance>
                        </accountbalance>
                        <accountbalance>
                              <glaccountno>7717</glaccountno>
                              <startbalance>0</startbalance>
                              <debits>2800</debits>
                              <credits>0.00</credits>
                              <adjdebits>0.00</adjdebits>
                              <adjcredits>0.00</adjcredits>
                              <endbalance>2800</endbalance>
                        </accountbalance>
                        <accountbalance>
                              <glaccountno>7719</glaccountno>
                              <startbalance>0</startbalance>
                              <debits>478.88</debits>
                              <credits>0.00</credits>
                              <adjdebits>0.00</adjdebits>
                              <adjcredits>0.00</adjcredits>
                              <endbalance>478.88</endbalance>
                        </accountbalance>
                        <accountbalance>
                              <glaccountno>7725</glaccountno>
                              <startbalance>0</startbalance>
                              <debits>23543.4</debits>
                              <credits>0.00</credits>
                              <adjdebits>0.00</adjdebits>
                              <adjcredits>0.00</adjcredits>
                              <endbalance>23543.4</endbalance>
                        </accountbalance>
                        <accountbalance>
                              <glaccountno>7727</glaccountno>
                              <startbalance>0</startbalance>
                              <debits>10002.26</debits>
                              <credits>0.00</credits>
                              <adjdebits>0.00</adjdebits>
                              <adjcredits>0.00</adjcredits>
                              <endbalance>10002.26</endbalance>
                        </accountbalance>
                        <accountbalance>
                              <glaccountno>7729</glaccountno>
                              <startbalance>0</startbalance>
                              <debits>1417.75</debits>
                              <credits>0.00</credits>
                              <adjdebits>0.00</adjdebits>
                              <adjcredits>0.00</adjcredits>
                              <endbalance>1417.75</endbalance>
                        </accountbalance>
                        <accountbalance>
                              <glaccountno>7733</glaccountno>
                              <startbalance>0</startbalance>
                              <debits>262.5</debits>
                              <credits>0.00</credits>
                              <adjdebits>0.00</adjdebits>
                              <adjcredits>0.00</adjcredits>
                              <endbalance>262.5</endbalance>
                        </accountbalance>
                        <accountbalance>
                              <glaccountno>8109</glaccountno>
                              <startbalance>0</startbalance>
                              <debits>0.00</debits>
                              <credits>3500</credits>
                              <adjdebits>0.00</adjdebits>
                              <adjcredits>0.00</adjcredits>
                              <endbalance>-3500</endbalance>
                        </accountbalance>
                  </data>
            </result>
      </operation>
</response>